forged/__init__.py
forged/client.py
forged_client-0.1.0.dist-info/METADATA
forged_client-0.1.0.dist-info/WHEEL
forged_client-0.1.0.dist-info/top_level.txt
forged_client-0.1.0.dist-info/RECORD
