Metadata-Version: 2.1
Name: forged-client
Version: 0.1.0
Summary: Forged.dev Client library
Author-email: Ryan Summers <ryan.summers@vertigo-designs.com>, Noah Hüsser <noah@huesser.dev>
Project-URL: Homepage, https://forged.dev
Keywords: api,client,database,embedded
Classifier: Development Status :: 3 - Alpha
Classifier: Intended Audience :: Developers
Classifier: Intended Audience :: Manufacturing
Classifier: License :: OSI Approved :: MIT License
Classifier: Topic :: Scientific/Engineering
Classifier: Topic :: System :: Hardware
Requires-Dist: gql[all]
